MANIFEST.in
README.md
VERSION
setup.py
ML_management/__init__.py
ML_management/collectors/__init__.py
ML_management/collectors/collector_pattern.py
ML_management/collectors/collector_pattern_to_methods_map.py
ML_management/collectors/collectors.py
ML_management/collectors/dummy/__init__.py
ML_management/collectors/dummy/dummy_collector.py
ML_management/collectors/s3/__init__.py
ML_management/collectors/s3/s3collector.py
ML_management/collectors/topic_markers/__init__.py
ML_management/collectors/topic_markers/api_schema.py
ML_management/collectors/topic_markers/topic_markers_collector.py
ML_management/dataset_loader/__init__.py
ML_management/dataset_loader/base_splits_dataset_loader.py
ML_management/dataset_loader/dataset_loader_pattern.py
ML_management/dataset_loader/dataset_loader_pattern_to_methods_map.py
ML_management/dataset_loader/poisoned_images_dataset_loader.py
ML_management/executor/__init__.py
ML_management/executor/base_executor.py
ML_management/executor/executor_pattern.py
ML_management/executor/executor_pattern_to_methods_map.py
ML_management/executor/no_model_executor_pattern.py
ML_management/executor/patterns.py
ML_management/executor/upload_model_mode.py
ML_management/executor/templates/__init__.py
ML_management/executor/templates/upload.py
ML_management/executor/templates/eval/__init__.py
ML_management/executor/templates/eval/conda.yaml
ML_management/executor/templates/eval/eval_executor.py
ML_management/executor/templates/finetune/__init__.py
ML_management/executor/templates/finetune/conda.yaml
ML_management/executor/templates/finetune/finetune_executor.py
ML_management/executor/templates/train/__init__.py
ML_management/executor/templates/train/conda.yaml
ML_management/executor/templates/train/train_executor.py
ML_management/loader/__init__.py
ML_management/loader/loader.py
ML_management/mlmanagement/__init__.py
ML_management/mlmanagement/abstract_mlflow_client.py
ML_management/mlmanagement/base_exceptions.py
ml_management.egg-info/PKG-INFO
ml_management.egg-info/SOURCES.txt
ml_management.egg-info/dependency_links.txt
ml_management.egg-info/requires.txt
ml_management.egg-info/top_level.txt