Metadata-Version: 2.1
Name: ml-management
Version: 0.3.0
Summary: Python implementation of model pattern, dataset
Home-page: UNKNOWN
Author: ISPRAS MODIS
Author-email: modis@ispras.ru
Maintainer: Maxim Ryndin
License: UNKNOWN
Platform: UNKNOWN
Requires-Python: >=3.8
